[
  {
    "name": "Cloud Native Days France 2026",
    "city": "Paris",
    "country": "France",
    "start_date": "2026-02-03",
    "website": "https://www.cloudnativedays.fr",
    "event_type": "conference",
    "end_date": "2026-02-03",
    "topics": [
      "Kubernetes",
      "Cloud Native",
      "DevOps",
      "Open Source",
      "Platform Engineering"
    ],
    "cfp_deadline": null,
    "cfp_url": null,
    "description": "Formerly known as Kubernetes Community Days (KCD) France, this community-driven event focuses on the latest innovations in Cloud Native technologies and DevOps practices.",
    "relevance_score": 0.7,
    "last_updated": "2026-02-03T17:37:56.488035",
    "id": "b36e3dc332bc"
  },
  {
    "name": "Q1 TLVCommunity Winter Blitz @ Aerospike",
    "city": "Tel Aviv",
    "country": "Israel",
    "start_date": "2026-02-03",
    "website": "https://www.meetup.com/israeli-aerospike-user-group/events/305886364/",
    "event_type": "meetup",
    "end_date": null,
    "topics": [
      "devops",
      "cloud native",
      "serverless",
      "statscraft"
    ],
    "cfp_deadline": null,
    "cfp_url": null,
    "description": "An evening of technical talks in collaboration with the TLVCommunity, featuring sessions on DevOps, Cloud Native, Serverless, and Statscraft.",
    "relevance_score": 0.7,
    "last_updated": "2026-02-03T17:39:51.321342",
    "id": "9910fd418183"
  },
  {
    "name": "AWS Brno Meetup: Building with GenAI & Autonomous Agents",
    "city": "Brno",
    "country": "Czech Republic",
    "start_date": "2026-02-05",
    "website": "https://www.meetup.com/devops-club-brno/",
    "event_type": "meetup",
    "end_date": "2026-02-05",
    "topics": [
      "devops",
      "cloud computing",
      "aws",
      "platform engineering",
      "infrastructure as code"
    ],
    "cfp_deadline": null,
    "cfp_url": null,
    "description": "Hosted by DevOps Club Brno, this technical meetup focuses on building and deploying containerized autonomous agents on AWS using Bedrock and CDK, covering infrastructure and orchestration for reliable AI systems.",
    "relevance_score": 0.7,
    "last_updated": "2026-02-03T17:41:09.422618",
    "id": "df492c01186e"
  },
  {
    "name": "Cloud Native & AI Day: Beyond ChatBots",
    "city": "Bangalore",
    "country": "India",
    "start_date": "2026-02-07",
    "website": "https://www.meetup.com/kubernetes-bangalore/",
    "event_type": "meetup",
    "end_date": "2026-02-07",
    "topics": [
      "Cloud Native",
      "Agentic Stack",
      "DevOps",
      "AI"
    ],
    "cfp_deadline": null,
    "cfp_url": "https://bit.ly/lmcfpsubmit",
    "description": "An insightful event focused on Cloud Native Platforms and the transition from automation to intelligence in infrastructure.",
    "relevance_score": 0.7,
    "last_updated": "2026-02-03T17:38:36.974339",
    "id": "2ebb3010b75d"
  },
  {
    "name": "Grafana & Friends x Observability India Happy Hours",
    "city": "Pune",
    "country": "India",
    "start_date": "2026-02-07",
    "website": "https://www.meetup.com/grafana-friends-pune/",
    "event_type": "meetup",
    "end_date": null,
    "topics": [
      "observability",
      "monitoring",
      "sre",
      "devops"
    ],
    "cfp_deadline": null,
    "cfp_url": null,
    "description": "A community gathering focused on observability practices, featuring technical talks on monitoring stacks and site reliability engineering.",
    "relevance_score": 0.7,
    "last_updated": "2026-02-03T17:39:15.546906",
    "id": "8042bb987a4d"
  },
  {
    "name": "Modern Data Platforms and Deployment Architectures",
    "city": "Pune",
    "country": "India",
    "start_date": "2026-02-07",
    "website": "https://www.meetup.com/pune-developers-community/",
    "event_type": "meetup",
    "end_date": null,
    "topics": [
      "microservices",
      "deployment",
      "platform engineering",
      "infrastructure"
    ],
    "cfp_deadline": null,
    "cfp_url": null,
    "description": "Hosted by the Pune Developer's Community, this session focuses on scaling microservices through modern deployment architectures and platform engineering strategies.",
    "relevance_score": 0.7,
    "last_updated": "2026-02-03T17:39:15.546912",
    "id": "7952f2f059c6"
  },
  {
    "name": "All Things Open RTP Meetup - February 2026",
    "city": "Raleigh",
    "country": "USA",
    "start_date": "2026-02-10",
    "website": "https://allthingsopen.org/events/february-2026-rtp-meetup/",
    "event_type": "meetup",
    "end_date": "2026-02-10",
    "topics": [
      "open source",
      "devops",
      "cloud native"
    ],
    "cfp_deadline": null,
    "cfp_url": null,
    "description": "A monthly meetup examining topics and technologies in the open source, tech, and web space, hosted by the All Things Open team.",
    "relevance_score": 0.7,
    "last_updated": "2026-02-03T17:40:20.732268",
    "id": "7ce4f184eac7"
  },
  {
    "name": "10th Edition India DevOps Show 2026",
    "city": "Bangalore",
    "country": "India",
    "start_date": "2026-02-13",
    "website": "https://indiadevopsshow.com/",
    "event_type": "conference",
    "end_date": "2026-02-13",
    "topics": [
      "DevOps",
      "CI/CD",
      "Agentic AI",
      "Orchestration"
    ],
    "cfp_deadline": null,
    "cfp_url": "https://indiadevopsshow.com/",
    "description": "Brings together top DevOps professionals to explore Agentic AI and the next frontier in DevOps evolution.",
    "relevance_score": 0.7,
    "last_updated": "2026-02-03T17:38:36.974366",
    "id": "1735f62447d1"
  },
  {
    "name": "DevConf.IN 2026",
    "city": "Pune",
    "country": "India",
    "start_date": "2026-02-13",
    "website": "https://devconf.info/in/",
    "event_type": "conference",
    "end_date": "2026-02-14",
    "topics": [
      "open source",
      "cloud native",
      "kubernetes",
      "devops",
      "platform engineering",
      "infrastructure as code"
    ],
    "cfp_deadline": "2025-11-21",
    "cfp_url": "https://pretalx.com/devconf-in-2026/cfp",
    "description": "DevConf.IN is a community-driven open-source conference organized by Red Hat. The 2026 edition in Pune features dedicated tracks for Cloud, Edge, and Platform Engineering, covering Kubernetes, DevOps, and sustainable computing.",
    "relevance_score": 0.7,
    "last_updated": "2026-02-03T17:39:15.546868",
    "id": "110441992259"
  },
  {
    "name": "ObservabilityCON on the Road - Paris",
    "city": "Paris",
    "country": "France",
    "start_date": "2026-02-19",
    "website": "https://grafana.com/about/events/",
    "event_type": "conference",
    "end_date": null,
    "topics": [
      "Observability",
      "DevOps",
      "SRE",
      "Grafana",
      "Prometheus"
    ],
    "cfp_deadline": null,
    "cfp_url": null,
    "description": "A focused event exploring the future of open source observability, including hands-on sessions on Grafana, Loki, and Tempo for DevOps and SRE teams.",
    "relevance_score": 0.7,
    "last_updated": "2026-02-03T17:37:56.488069",
    "id": "44015bfef144"
  },
  {
    "name": "Test Automation Summit Bangalore 2026",
    "city": "Bangalore",
    "country": "India",
    "start_date": "2026-02-19",
    "website": "https://10times.com/test-automation-summit-bangalore",
    "event_type": "conference",
    "end_date": "2026-02-19",
    "topics": [
      "Test Automation",
      "CI/CD",
      "Quality Engineering"
    ],
    "cfp_deadline": null,
    "cfp_url": null,
    "description": "Focused on the latest trends in test automation and its integration into continuous delivery pipelines.",
    "relevance_score": 0.7,
    "last_updated": "2026-02-03T17:38:36.974372",
    "id": "7fc66f022cb4"
  },
  {
    "name": "Test Automation Summit Pune 2026",
    "city": "Pune",
    "country": "India",
    "start_date": "2026-02-26",
    "website": "https://testautomationsummit.com/pune/",
    "event_type": "conference",
    "end_date": null,
    "topics": [
      "continuous integration",
      "test automation",
      "devops",
      "quality engineering"
    ],
    "cfp_deadline": null,
    "cfp_url": null,
    "description": "A specialized conference focusing on the latest trends in software testing automation, including CI/CD integration and AI-driven quality assurance.",
    "relevance_score": 0.7,
    "last_updated": "2026-02-03T17:39:15.546899",
    "id": "c5c261d0d7d1"
  },
  {
    "name": "11th Edition DevOps Conclave & Awards 2026",
    "city": "Bangalore",
    "country": "India",
    "start_date": "2026-03-13",
    "website": "https://devopsconclave.com/",
    "event_type": "conference",
    "end_date": "2026-03-13",
    "topics": [
      "DevOps",
      "Kubernetes",
      "GitOps",
      "Platform Engineering"
    ],
    "cfp_deadline": null,
    "cfp_url": "https://devopsconclave.com/",
    "description": "Explores emerging trends like AIOps, FinOps, and developer experience optimization in the DevOps ecosystem.",
    "relevance_score": 0.7,
    "last_updated": "2026-02-03T17:38:36.974376",
    "id": "aeca1520a474"
  },
  {
    "name": "AWS Community Day Pune 2026",
    "city": "Pune",
    "country": "India",
    "start_date": "2026-03-21",
    "website": "https://awsugpune.in/",
    "event_type": "conference",
    "end_date": null,
    "topics": [
      "aws",
      "cloud computing",
      "devops",
      "serverless",
      "infrastructure"
    ],
    "cfp_deadline": null,
    "cfp_url": null,
    "description": "A community-led event for AWS users and enthusiasts in Pune. The conference focuses on real-world cloud implementations, DevOps practices on AWS, and emerging cloud technologies.",
    "relevance_score": 0.7,
    "last_updated": "2026-02-03T17:39:15.546889",
    "id": "77736da5e324"
  },
  {
    "name": "Ceph Days Raleigh 2026",
    "city": "Raleigh",
    "country": "USA",
    "start_date": "2026-03-25",
    "website": "https://ceph.io/en/news/blog/2025/ceph-days-raleigh-2026/",
    "event_type": "conference",
    "end_date": "2026-03-25",
    "topics": [
      "storage",
      "kubernetes",
      "openshift",
      "platform engineering"
    ],
    "cfp_deadline": "2026-02-16",
    "cfp_url": "https://ceph.io/en/news/blog/2025/ceph-days-raleigh-2026/",
    "description": "A full-day event dedicated to Ceph storage and its integrations with platforms like Kubernetes and OpenShift.",
    "relevance_score": 0.7,
    "last_updated": "2026-02-03T17:40:20.732272",
    "id": "db75fde66796"
  },
  {
    "name": "AWS Summit Paris 2026",
    "city": "Paris",
    "country": "France",
    "start_date": "2026-04-01",
    "website": "https://aws.amazon.com/summits/paris/",
    "event_type": "conference",
    "end_date": "2026-04-01",
    "topics": [
      "Cloud Computing",
      "DevOps",
      "Serverless",
      "Infrastructure as Code",
      "AWS"
    ],
    "cfp_deadline": null,
    "cfp_url": null,
    "description": "The largest AWS event in France, featuring technical sessions on cloud architecture, DevOps automation, and scaling applications in the cloud.",
    "relevance_score": 0.7,
    "last_updated": "2026-02-03T17:37:56.488081",
    "id": "c8c9cc5f530f"
  },
  {
    "name": "QonfX 2026 Bangalore",
    "city": "Bangalore",
    "country": "India",
    "start_date": "2026-04-10",
    "website": "https://thetesttribe.com/qonfx-bangalore/",
    "event_type": "conference",
    "end_date": "2026-04-10",
    "topics": [
      "Platform Engineering",
      "Testing",
      "DevOps"
    ],
    "cfp_deadline": null,
    "cfp_url": null,
    "description": "An invite-only conference for QA and tech leaders featuring deep dives into Platform Engineering to achieve quality with speed.",
    "relevance_score": 0.7,
    "last_updated": "2026-02-03T17:38:36.974379",
    "id": "ad6236865329"
  },
  {
    "name": "Great International Developer Summit (GIDS) 2026",
    "city": "Bangalore",
    "country": "India",
    "start_date": "2026-04-21",
    "website": "https://developersummit.com/",
    "event_type": "conference",
    "end_date": "2026-04-24",
    "topics": [
      "Software Architecture",
      "DevOps",
      "Cloud Native",
      "Platform Engineering"
    ],
    "cfp_deadline": null,
    "cfp_url": "https://developersummit.com/",
    "description": "Asia's largest polyglot software conference covering the full technology spectrum, including extensive DevOps and architecture tracks.",
    "relevance_score": 0.7,
    "last_updated": "2026-02-03T17:38:36.974382",
    "id": "23b0810961fa"
  },
  {
    "name": "Devoxx France 2026",
    "city": "Paris",
    "country": "France",
    "start_date": "2026-04-22",
    "website": "https://www.devoxx.fr",
    "event_type": "conference",
    "end_date": "2026-04-24",
    "topics": [
      "Java",
      "Cloud",
      "DevOps",
      "CI/CD",
      "Software Architecture"
    ],
    "cfp_deadline": "2026-01-31",
    "cfp_url": "https://devoxxfr2026.cfp.dev",
    "description": "The largest independent developer conference in France with dedicated tracks for Cloud, DevOps, and modern CI/CD practices.",
    "relevance_score": 0.7,
    "last_updated": "2026-02-03T17:37:56.488089",
    "id": "6483af00ebb1"
  },
  {
    "name": "Agile DevOps Conference 2026",
    "city": "Bangalore",
    "country": "India",
    "start_date": "2026-04-23",
    "website": "https://navigoseminars.com/",
    "event_type": "conference",
    "end_date": "2026-04-23",
    "topics": [
      "Agile",
      "DevOps",
      "CI/CD",
      "Continuous Delivery"
    ],
    "cfp_deadline": null,
    "cfp_url": "https://navigoseminars.com/",
    "description": "Focuses on building resilient CI/CD pipelines and scaling Agile and DevOps practices across complex enterprise environments.",
    "relevance_score": 0.7,
    "last_updated": "2026-02-03T17:38:36.974385",
    "id": "4857eae7b003"
  },
  {
    "name": "Gophercamp.cz 2026",
    "city": "Brno",
    "country": "Czech Republic",
    "start_date": "2026-04-23",
    "website": "https://gophercamp.cz/",
    "event_type": "conference",
    "end_date": "2026-04-24",
    "topics": [
      "golang",
      "cloud native",
      "kubernetes",
      "devops"
    ],
    "cfp_deadline": null,
    "cfp_url": null,
    "description": "A technical conference dedicated to the Go programming language, focusing on its use in building robust cloud-native infrastructure, tools, and scalable systems.",
    "relevance_score": 0.7,
    "last_updated": "2026-02-03T17:41:09.422635",
    "id": "26b0b0dfeac1"
  },
  {
    "name": "DevOpsDays Raleigh 2026",
    "city": "Raleigh",
    "country": "USA",
    "start_date": "2026-04-30",
    "website": "https://devopsdays.org/events/2026-raleigh/welcome/",
    "event_type": "conference",
    "end_date": "2026-05-01",
    "topics": [
      "devops",
      "ci/cd",
      "platform engineering",
      "automation"
    ],
    "cfp_deadline": null,
    "cfp_url": "https://devopsdays.org/events/2026-raleigh/propose",
    "description": "The 10th anniversary celebration of DevOpsDays Raleigh, focusing on software development, IT operations, and the intersection between them.",
    "relevance_score": 0.7,
    "last_updated": "2026-02-03T17:40:20.732274",
    "id": "760893cf2350"
  },
  {
    "name": "OWASP AppSec Days Israel 2026",
    "city": "Tel Aviv",
    "country": "Israel",
    "start_date": "2026-05-18",
    "website": "https://dev.events/conferences/owasp-appsec-days-israel-2026-tel-aviv",
    "event_type": "conference",
    "end_date": null,
    "topics": [
      "cybersecurity",
      "appsec",
      "devsecops"
    ],
    "cfp_deadline": null,
    "cfp_url": null,
    "description": "The premier application security conference in Israel, focusing on secure development, DevSecOps, and modern cybersecurity practices.",
    "relevance_score": 0.7,
    "last_updated": "2026-02-03T17:39:51.321346",
    "id": "cf54c8b37ace"
  },
  {
    "name": "AFUP Day Paris 2026",
    "city": "Paris",
    "country": "France",
    "start_date": "2026-05-22",
    "website": "https://afup.org/events/",
    "event_type": "conference",
    "end_date": "2026-05-22",
    "topics": [
      "PHP",
      "Cloud",
      "DevOps",
      "CI/CD",
      "Containers"
    ],
    "cfp_deadline": null,
    "cfp_url": null,
    "description": "A technical conference that, while focused on the PHP ecosystem, consistently features strong tracks on DevOps, cloud-native deployments, and containerization.",
    "relevance_score": 0.7,
    "last_updated": "2026-02-03T17:37:56.488095",
    "id": "3ce755243d08"
  },
  {
    "name": "PlatforMa 2026",
    "city": "Tel Aviv",
    "country": "Israel",
    "start_date": "2026-05-26",
    "website": "https://www.platfor-ma.com/",
    "event_type": "conference",
    "end_date": null,
    "topics": [
      "platform engineering",
      "infrastructure management",
      "devops",
      "developer experience"
    ],
    "cfp_deadline": "2026-01-31",
    "cfp_url": "https://sessionize.com/platforma-2026",
    "description": "Israel's premier conference dedicated to Platform Engineering, bringing together experts to discuss developer portals, internal developer platforms (IDPs), and delivery acceleration.",
    "relevance_score": 0.7,
    "last_updated": "2026-02-03T17:39:51.321348",
    "id": "2d2d53d30eca"
  },
  {
    "name": "Regional Scrum Gathering (RSG) Pune 2026",
    "city": "Pune",
    "country": "India",
    "start_date": "2026-06-12",
    "website": "https://icaaionline.org/rsgpune2026",
    "event_type": "conference",
    "end_date": "2026-06-13",
    "topics": [
      "agile",
      "scrum",
      "devops",
      "ai in engineering"
    ],
    "cfp_deadline": null,
    "cfp_url": null,
    "description": "Organized by the Indian Circle of Agile & AI, this gathering brings together industry leaders to discuss Agile transformations, DevOps culture, and the impact of AI on software delivery.",
    "relevance_score": 0.7,
    "last_updated": "2026-02-03T17:39:15.546903",
    "id": "5152a7a52f69"
  },
  {
    "name": "DevConf.cz 2026",
    "city": "Brno",
    "country": "Czech Republic",
    "start_date": "2026-06-18",
    "website": "https://www.devconf.info/cz/",
    "event_type": "conference",
    "end_date": "2026-06-19",
    "topics": [
      "devops",
      "ci/cd",
      "kubernetes",
      "cloud native",
      "platform engineering",
      "automation",
      "containers"
    ],
    "cfp_deadline": "2026-03-01",
    "cfp_url": "https://www.devconf.info/cz/",
    "description": "An annual free open-source community conference sponsored by Red Hat. It covers a wide range of topics including cloud infrastructure, Kubernetes, DevOps, CI/CD pipelines, and platform engineering at scale.",
    "relevance_score": 0.7,
    "last_updated": "2026-02-03T17:41:09.422639",
    "id": "ecba2306cc26"
  },
  {
    "name": "Open Source India 2026",
    "city": "Bangalore",
    "country": "India",
    "start_date": "2026-10-07",
    "website": "https://opensourceindia.in/",
    "event_type": "conference",
    "end_date": "2026-10-08",
    "topics": [
      "Open Source",
      "Platform Engineering",
      "Cloud Native",
      "Infrastructure as Code"
    ],
    "cfp_deadline": null,
    "cfp_url": "https://opensourceindia.in/",
    "description": "India's premier open-source event featuring workshops and sessions on cloud native infrastructure and platform services.",
    "relevance_score": 0.7,
    "last_updated": "2026-02-03T17:38:36.974388",
    "id": "33285bbfafee"
  },
  {
    "name": "GopherCon Israel 2026",
    "city": "Tel Aviv",
    "country": "Israel",
    "start_date": "2026-10-18",
    "website": "https://dev.events/conferences/gophercon-israel-2026-tel-aviv",
    "event_type": "conference",
    "end_date": null,
    "topics": [
      "golang",
      "cloud native",
      "kubernetes",
      "backend engineering"
    ],
    "cfp_deadline": null,
    "cfp_url": null,
    "description": "The local edition of the global Golang conference, highly relevant to developers building cloud-native systems and Kubernetes operators with Go.",
    "relevance_score": 0.7,
    "last_updated": "2026-02-03T17:39:51.321350",
    "id": "b4b70eafd588"
  },
  {
    "name": "All Things Open 2026",
    "city": "Raleigh",
    "country": "USA",
    "start_date": "2026-10-18",
    "website": "https://allthingsopen.org/",
    "event_type": "conference",
    "end_date": "2026-10-20",
    "topics": [
      "open source",
      "devops",
      "cloud native",
      "ci/cd",
      "ai"
    ],
    "cfp_deadline": null,
    "cfp_url": "https://allthingsopen.org/call-for-papers/",
    "description": "One of the largest open source and open tech conferences on the U.S. East Coast, featuring dedicated tracks for DevOps and Cloud Native technologies.",
    "relevance_score": 0.7,
    "last_updated": "2026-02-03T17:40:20.732276",
    "id": "45161a79b785"
  },
  {
    "name": "Cloud & AI Infrastructure Paris 2026",
    "city": "Paris",
    "country": "France",
    "start_date": "2026-11-18",
    "website": "https://www.techshowparis.fr/cloud-ai-infrastructure-paris",
    "event_type": "conference",
    "end_date": "2026-11-19",
    "topics": [
      "Cloud Infrastructure",
      "DevOps",
      "CI/CD",
      "Data Centers",
      "FinOps"
    ],
    "cfp_deadline": null,
    "cfp_url": null,
    "description": "Formerly Cloud Expo Europe Paris, this event brings together IT decision-makers and architects to discuss the evolution of cloud infrastructure, hybrid strategies, and DevOps tools.",
    "relevance_score": 0.7,
    "last_updated": "2026-02-03T17:37:56.488100",
    "id": "ea03aa44034c"
  },
  {
    "name": "Bengaluru Tech Summit 2026",
    "city": "Bangalore",
    "country": "India",
    "start_date": "2026-11-18",
    "website": "https://bengalurutechsummit.com/",
    "event_type": "conference",
    "end_date": "2026-11-20",
    "topics": [
      "Innovation",
      "Cloud",
      "DevOps",
      "Enterprise Tech"
    ],
    "cfp_deadline": null,
    "cfp_url": null,
    "description": "A massive annual summit covering a broad range of technologies, including significant sessions on cloud-driven operations and DevOps.",
    "relevance_score": 0.7,
    "last_updated": "2026-02-03T17:38:36.974391",
    "id": "db3c43a722b2"
  },
  {
    "name": "apidays Paris 2026",
    "city": "Paris",
    "country": "France",
    "start_date": "2026-11-30",
    "website": "https://www.apidays.global/paris/",
    "event_type": "conference",
    "end_date": "2026-12-03",
    "topics": [
      "APIs",
      "Platform Engineering",
      "Automation",
      "Architecture"
    ],
    "cfp_deadline": null,
    "cfp_url": "https://www.apidays.global/paris/",
    "description": "A major event focused on API ecosystems, featuring sessions on platform engineering, developer experience (DevEx), and automated delivery.",
    "relevance_score": 0.7,
    "last_updated": "2026-02-03T17:37:56.488105",
    "id": "bf44a8d9e027"
  },
  {
    "name": "DevOps REX 2026",
    "city": "Paris",
    "country": "France",
    "start_date": "2026-12-10",
    "website": "https://www.devopsrex.fr",
    "event_type": "conference",
    "end_date": "2026-12-11",
    "topics": [
      "DevOps",
      "CI/CD",
      "SRE",
      "Continuous Delivery",
      "Feedback"
    ],
    "cfp_deadline": null,
    "cfp_url": null,
    "description": "The 'experience feedback' conference for the DevOps community. Co-located with Open Source Experience, it focuses on real-world implementations, failures, and successes.",
    "relevance_score": 0.7,
    "last_updated": "2026-02-03T17:37:56.488109",
    "id": "28a33c17deab"
  },
  {
    "name": "Open Source Experience 2026",
    "city": "Paris",
    "country": "France",
    "start_date": "2026-12-10",
    "website": "https://www.opensource-experience.com/",
    "event_type": "conference",
    "end_date": "2026-12-11",
    "topics": [
      "Open Source",
      "Cloud",
      "Kubernetes",
      "Cybersecurity",
      "DevOps"
    ],
    "cfp_deadline": null,
    "cfp_url": null,
    "description": "Europe's meeting place for the open source ecosystem, highlighting innovative solutions in cloud computing, containers, and automated infrastructure.",
    "relevance_score": 0.7,
    "last_updated": "2026-02-03T17:37:56.488114",
    "id": "049edb9fec9e"
  },
  {
    "name": "Cybertech Global TLV 2027",
    "city": "Tel Aviv",
    "country": "Israel",
    "start_date": "2027-01-25",
    "website": "https://www.cybertechisrael.com/",
    "event_type": "conference",
    "end_date": "2027-01-27",
    "topics": [
      "cybersecurity",
      "cloud security",
      "innovation"
    ],
    "cfp_deadline": null,
    "cfp_url": null,
    "description": "A massive international cybersecurity event that includes significant tracks and networking opportunities for cloud security and DevOps professionals.",
    "relevance_score": 0.7,
    "last_updated": "2026-02-03T17:39:51.321352",
    "id": "f5939a405b4e"
  },
  {
    "name": "AWS Summit Paris 2027",
    "city": "Paris",
    "country": "France",
    "start_date": "2027-04-01",
    "website": "https://aws.amazon.com/summits/paris/",
    "event_type": "conference",
    "end_date": "2027-04-01",
    "topics": [
      "Cloud Computing",
      "DevOps",
      "Platform Engineering",
      "AWS"
    ],
    "cfp_deadline": null,
    "cfp_url": null,
    "description": "Projected return of the AWS flagship event in Paris, expected to focus on serverless evolution, DevOps automation, and AI-driven platforms.",
    "relevance_score": 0.7,
    "last_updated": "2026-02-03T17:37:56.488118",
    "id": "b7482aa1a980"
  }
]